aicode/__init__.py
aiCode-23.6.22.0.dist-info/LICENSE
aiCode-23.6.22.0.dist-info/METADATA
aiCode-23.6.22.0.dist-info/WHEEL
aiCode-23.6.22.0.dist-info/top_level.txt
aiCode-23.6.22.0.dist-info/zip-safe
aiCode-23.6.22.0.dist-info/RECORD
